[{
	"name": "waynejohnson",
	"url": "https://waynejohnson.net",
	"xpath": "/html/body/div[3]/div[1]/p[1]"
},
{
	"name": "Drive Manual",
	"url": "https://www.drive.com.au/car-sales?search=1&sortBy=1&priceMax=50000&make=Holden&model=Astra&location=&yearMin=2016&yearMax=&kmsMin=&kmsMax=&seller=&seats=&doors=&transmission=manual",
	"xpath": "/html/body/div[8]/div/main/div/div[1]/div[5]/div",
	"headers": [{
		"name": "Host",
		"value": "www.drive.com.au"
	},
	{
		"name": "User-Agent",
		"value": "Mozilla/5.0 (Windows NT 10.0; Win64; x64; rv:66.0) Gecko/20100101 Firefox/66.0"
	},
	{
		"name": "Accept",
		"value": "text/html,application/xhtml+xml,application/xml;q=0.9,*/*;q=0.8"
	},
	{
		"name": "Accept-Language",
		"value": "en-AU,en;q=0.5"
	},
	{
		"name": "Accept-Encoding",
		"value": "gzip, deflate, br"
	},
	{
		"name": "DNT",
		"value": "1"
	},
	{
		"name": "Connection",
		"value": "keep-alive"
	},
	{
		"name": "Upgrade-Insecure-Requests",
		"value": "1"
	}]
},
{
	"name": "McGrath Regional",
	"url": "https://mcgrathautogroup.com.au/new-demo-used-cars-canberra.html?make=Holden&model=Astra&gearbox=",
	"xpath": "/html/body/div[1]/div[2]/div/div[2]/div[1]",
	"headers": [{
		"name": "Host",
		"value": "mcgrathautogroup.com.au"
	},
	{
		"name": "Accept",
		"value": "text/html,application/xhtml+xml,application/xml;q=0.9,*/*;q=0.8"
	},
	{
		"name": "Accept-Language",
		"value": "en-AU,en;q=0.5"
	},
	{
		"name": "Referer",
		"value": "https://mcgrathautogroup.com.au/"
	},
	{
		"name": "DNT",
		"value": "1"
	},
	{
		"name": "Connection",
		"value": "keep-alive"
	},
	{
		"name": "Upgrade-Insecure-Requests",
		"value": "1"
	},
	{
		"name": "TE",
		"value": "Trailers"
	}]
}]